[
  {
    "displayName": "Erick Tran",
    "firstName": "Erick",
    "lastName": "Tran",
    "email": "1071039@student.auhsd.us",
    "profilePicture": "https://lh3.googleusercontent.com/a/AAcHTtcnGDgbPNcDTK38ue9aN6Fb2CDx9ib0S0hjj9gt=s96-c",
    "hd": "student.auhsd.us",
    "hasAccessTo": {
      "CSD": {
        "hasAccess": true,
        "Assignments": {}
      },
      "CSP": {
        "hasAccess": true,
        "Assignments": {}
      },
      "CSA": {
        "hasAccess": true,
        "Assignments": {}
      },
      "MobileWebDev": {
        "hasAccess": true,
        "Assignments": {}
      },
      "AdminPanel": {
        "hasAccess": true,
        "Assignments": {}
      }
    },
    "unchangeableSettings": {
      "isLoggedin": true,
      "latestTimeLoggedIn": "Sat Jun 03 2023 13:08:04",
      "dayToLogOut": "Sat Jun 10 2023 13:08:04",
      "isStudent": true,
      "isStaff": false,
      "latestIPAddress": "VAf@*!)|}:VAf@*!)|}:NF(@#&:;><",
      "isLockedOut": false
    },
    "data_id": "6179989795161116645335782097605667864530855995255916814103367242"
  }
]